[
  {
    "name": "Patricio López",
    "career": "Ingeniería"
  },
  {
    "name": "Benjamín Vicente Goecke",
    "career": "Ingeniería"
  },
  {
    "name": "Agustín Covarrubias",
    "career": "Ingeniería"
  },
  { 
    "name": "Vicente Muñoz",
    "career": "Licenciatura en Ingeniería en Ciencia de Datos"
  },
{
    "name": "Ignacio Palma",
    "career": "Licenciatura en Ingeniería en Ciencia de Datos"
  },
  {
    "name": "Mauricio Cari Leal",
    "career": "Ingeniería"
  },
  {
    "name": "Felipe Aguilar",
    "career": "Ingeniería"
  },
  {
    "name": "Diego Costa",
    "career": "Ingeniería"
  },
  {
    "name": "Víctor Moreno",
    "career": "Licenciatura en Ingeniería en Ciencia de la Computación"
  },
  {
    "name": "Pablo Cruzat",
    "career": "Licenciatura en Ingeniería en Ciencia de la Computación"
  },
  {
    "name": "Daniela Victoreo",
    "career": "Licenciatura en Ingeniería en Ciencia de Datos"
  },
  {
    "name": "Benjamín Cheuquian",
    "career": "Licenciatura en Ingeniería en Ciencia de Datos"
  },
  {
    "name": "Mané Schwarz",
    "career": "Licenciatura en Ingeniería en Ciencia de la Computación"
  },
  {
    "name": "Matías Fernández",
    "career": "Ingeniería"
  }
]