{
    "type": "FeatureCollection",
    "features": [
        {
            "type": "Feature",
            "geometry": {
                "type": "Point",
                "coordinates": [
                    -72.22495950989237,
                    -39.2771617067288
                ]
            },
            "properties": {
                "identifier": "MJD240QT1IHPRE",
                "name": "Auditorio",
                "information": "",
                "categories": [
                    "auditorium"
                ],
                "floors": [
                    1
                ],
                "needApproval": true,
                "campus": "VR",
                "faculties": []
            }
        },
        {
            "type": "Feature",
            "geometry": {
                "type": "Point",
                "coordinates": [
                    -72.22575542661136,
                    -39.2776236430512
                ]
            },
            "properties": {
                "identifier": "MJD22CS33IUMXH",
                "name": "Pastoral UC",
                "information": "",
                "categories": [
                    "other"
                ],
                "floors": [
                    -1
                ],
                "needApproval": true,
                "campus": "VR",
                "faculties": []
            }
        },
        {
            "type": "Feature",
            "geometry": {
                "type": "Point",
                "coordinates": [
                    -72.22584405890171,
                    -39.27771519289583
                ]
            },
            "properties": {
                "identifier": "MJD21I7FLL2TDT",
                "name": "Centro de Estudiantes CEV",
                "information": "",
                "categories": [
                    "other"
                ],
                "floors": [
                    1
                ],
                "needApproval": true,
                "campus": "VR",
                "faculties": []
            }
        },
        {
            "type": "Feature",
            "geometry": {
                "type": "Point",
                "coordinates": [
                    -72.22548600213413,
                    -39.27757938202303
                ]
            },
            "properties": {
                "identifier": "MJCW8323VTHQYM",
                "name": "Baño",
                "information": "",
                "categories": [
                    "bath"
                ],
                "floors": [
                    1
                ],
                "needApproval": true,
                "campus": "VR",
                "faculties": []
            }
        },
        {
            "type": "Feature",
            "geometry": {
                "type": "Point",
                "coordinates": [
                    -72.22542356394722,
                    -39.27760582003359
                ]
            },
            "properties": {
                "identifier": "MJCW7E8Y8WBPV5",
                "name": "Baño",
                "information": "",
                "categories": [
                    "bath"
                ],
                "floors": [
                    1
                ],
                "needApproval": true,
                "campus": "VR",
                "faculties": []
            }
        },
        {
            "type": "Feature",
            "geometry": {
                "type": "Point",
                "coordinates": [
                    -72.22575208482809,
                    -39.27768382009687
                ]
            },
            "properties": {
                "identifier": "MJCW2PFE2L6XA0",
                "name": "Baño",
                "information": "",
                "categories": [
                    "bath"
                ],
                "floors": [
                    1
                ],
                "needApproval": true,
                "campus": "VR",
                "faculties": []
            }
        },
        {
            "type": "Feature",
            "geometry": {
                "type": "Point",
                "coordinates": [
                    -72.2258046639059,
                    -39.27765385217351
                ]
            },
            "properties": {
                "identifier": "MJCW21VP0GUA8G",
                "name": "Baño",
                "information": "",
                "categories": [
                    "bath"
                ],
                "floors": [
                    1
                ],
                "needApproval": true,
                "campus": "VR",
                "faculties": []
            }
        },
        {
            "type": "Feature",
            "geometry": {
                "type": "Point",
                "coordinates": [
                    -70.59359593610766,
                    -33.44702190919684
                ]
            },
            "properties": {
                "identifier": "MJA6U32J2OS64O",
                "name": "Administración ",
                "information": "",
                "categories": [
                    "other"
                ],
                "floors": [
                    1
                ],
                "needApproval": true,
                "campus": "OR",
                "faculties": []
            }
        }
    ]
}