{
    "type": "FeatureCollection",
    "features": [
        {
            "type": "Feature",
            "properties": {
                "identifier": "SALA_6-OR",
                "name": "Sala 6",
                "information": "",
                "categories": [
                    "classroom"
                ],
                "campus": "OR",
                "faculties": "",
                "floors": [
                    1
                ],
                "needApproval": true
            },
            "geometry": {
                "type": "Point",
                "coordinates": [
                    -70.59313581162402,
                    -33.446286267905855
                ]
            }
        },
        {
            "type": "Feature",
            "properties": {
                "identifier": "ESPACIO_ESCÉNICO_ALBERTO_VEGA-OR",
                "name": "Espacio Escénico Alberto Vega",
                "information": "",
                "categories": [
                    "classroom"
                ],
                "campus": "OR",
                "faculties": "",
                "floors": [
                    1
                ],
                "needApproval": true
            },
            "geometry": {
                "type": "Point",
                "coordinates": [
                    -70.59301357135166,
                    -33.4463791152772
                ]
            }
        },
        {
            "type": "Feature",
            "properties": {
                "identifier": "SALA_2-OR",
                "name": "Sala 2",
                "information": "",
                "categories": [
                    "classroom"
                ],
                "campus": "OR",
                "faculties": "",
                "floors": [
                    1
                ],
                "needApproval": true
            },
            "geometry": {
                "type": "Point",
                "coordinates": [
                    -70.59308252074258,
                    -33.446257885033404
                ]
            }
        },
        {
            "type": "Feature",
            "properties": {
                "identifier": "SALA_4-OR",
                "name": "Sala 4",
                "information": "",
                "categories": [
                    "classroom"
                ],
                "campus": "OR",
                "faculties": "",
                "floors": [
                    1
                ],
                "needApproval": true
            },
            "geometry": {
                "type": "Point",
                "coordinates": [
                    -70.59309328397191,
                    -33.44626930955323
                ]
            }
        },
        {
            "type": "Feature",
            "properties": {
                "identifier": "SALA_DE_MAQUILLAJE-OR",
                "name": "Sala de maquillaje",
                "information": "",
                "categories": [
                    "classroom"
                ],
                "campus": "OR",
                "faculties": "",
                "floors": [
                    1
                ],
                "needApproval": true
            },
            "geometry": {
                "type": "Point",
                "coordinates": [
                    -70.59310097546303,
                    -33.4462661592628
                ]
            }
        },
        {
            "type": "Feature",
            "properties": {
                "identifier": "m8t6uhwnupbu82",
                "name": "Baño",
                "information": "",
                "categories": [
                    "bath"
                ],
                "campus": "OR",
                "faculties": "",
                "floors": [
                    1
                ],
                "needApproval": true
            },
            "geometry": {
                "type": "Point",
                "coordinates": [
                    -70.5930562132286,
                    -33.446203527565835
                ]
            }
        },
        {
            "type": "Feature",
            "properties": {
                "identifier": "m8t6uh1d2gl7v7",
                "name": "Baño",
                "information": "",
                "categories": [
                    "bath"
                ],
                "campus": "OR",
                "faculties": "",
                "floors": [
                    1
                ],
                "needApproval": true
            },
            "geometry": {
                "type": "Point",
                "coordinates": [
                    -70.5930562132286,
                    -33.446203527565835
                ]
            }
        },
        {
            "type": "Feature",
            "properties": {
                "identifier": "SALA_1-OR",
                "name": "Sala 1",
                "information": "",
                "categories": [
                    "classroom"
                ],
                "campus": "OR",
                "faculties": "",
                "floors": [
                    1
                ],
                "needApproval": true
            },
            "geometry": {
                "type": "Point",
                "coordinates": [
                    -70.59310231768193,
                    -33.4462447324955
                ]
            }
        },
        {
            "type": "Feature",
            "properties": {
                "identifier": "SALA_3-OR",
                "name": "Sala 3",
                "information": "",
                "categories": [
                    "classroom"
                ],
                "campus": "OR",
                "faculties": "",
                "floors": [
                    1
                ],
                "needApproval": true
            },
            "geometry": {
                "type": "Point",
                "coordinates": [
                    -70.59311358970513,
                    -33.446258178805266
                ]
            }
        },
        {
            "type": "Feature",
            "properties": {
                "identifier": "m8t6qd1jdrbcg3",
                "name": "English UC",
                "information": "",
                "categories": [
                    "other"
                ],
                "campus": "OR",
                "faculties": "",
                "floors": [
                    1
                ],
                "needApproval": true
            },
            "geometry": {
                "type": "Point",
                "coordinates": [
                    -70.59339106301933,
                    -33.446469089093746
                ]
            }
        },
        {
            "type": "Feature",
            "properties": {
                "identifier": "E101-OR",
                "name": "E101",
                "information": "",
                "categories": [
                    "classroom"
                ],
                "campus": "OR",
                "faculties": "",
                "floors": [
                    1
                ],
                "needApproval": true
            },
            "geometry": {
                "type": "Point",
                "coordinates": [
                    -70.5934533570796,
                    -33.446391207079834
                ]
            }
        },
        {
            "type": "Feature",
            "properties": {
                "identifier": "E102-OR",
                "name": "E102",
                "information": "",
                "categories": [
                    "classroom"
                ],
                "campus": "OR",
                "faculties": "",
                "floors": [
                    1
                ],
                "needApproval": true
            },
            "geometry": {
                "type": "Point",
                "coordinates": [
                    -70.59363855093596,
                    -33.446375013859395
                ]
            }
        },
        {
            "type": "Feature",
            "properties": {
                "identifier": "E103-OR",
                "name": "E103",
                "information": "",
                "categories": [
                    "classroom"
                ],
                "campus": "OR",
                "faculties": "",
                "floors": [
                    1
                ],
                "needApproval": true
            },
            "geometry": {
                "type": "Point",
                "coordinates": [
                    -70.59369043480794,
                    -33.44626242649246
                ]
            }
        },
        {
            "type": "Feature",
            "properties": {
                "identifier": "m8t6o0gookdlyq",
                "name": "Centro de extensión oriente",
                "information": "",
                "categories": [
                    "other"
                ],
                "campus": "OR",
                "faculties": "",
                "floors": [
                    1
                ],
                "needApproval": true
            },
            "geometry": {
                "type": "Point",
                "coordinates": [
                    -70.59379196291492,
                    -33.44639824347777
                ]
            }
        },
        {
            "type": "Feature",
            "properties": {
                "identifier": "m8t6nz7bwpebm9",
                "name": "Centro de extensión oriente",
                "information": "",
                "categories": [
                    "other"
                ],
                "campus": "OR",
                "faculties": "",
                "floors": [
                    1
                ],
                "needApproval": true
            },
            "geometry": {
                "type": "Point",
                "coordinates": [
                    -70.59379196291492,
                    -33.44639824347777
                ]
            }
        },
        {
            "type": "Feature",
            "properties": {
                "identifier": "AULA_DE_ARTE_Y_ARTESANÍAS-OR",
                "name": "Aula de Arte y Artesanías",
                "information": "",
                "categories": [
                    "classroom"
                ],
                "campus": "OR",
                "faculties": "",
                "floors": [
                    1
                ],
                "needApproval": true
            },
            "geometry": {
                "type": "Point",
                "coordinates": [
                    -70.59381416866758,
                    -33.446583314773115
                ]
            }
        },
        {
            "type": "Feature",
            "properties": {
                "identifier": "m8t6jqlkhu8y1w",
                "name": "Baño",
                "information": "",
                "categories": [
                    "bath"
                ],
                "campus": "OR",
                "faculties": "",
                "floors": [
                    -1
                ],
                "needApproval": true
            },
            "geometry": {
                "type": "Point",
                "coordinates": [
                    -70.59376182300412,
                    -33.44640990906889
                ]
            }
        },
        {
            "type": "Feature",
            "properties": {
                "identifier": "m8t6jpvvayi84e",
                "name": "Baño",
                "information": "",
                "categories": [
                    "bath"
                ],
                "campus": "OR",
                "faculties": "",
                "floors": [
                    -1
                ],
                "needApproval": true
            },
            "geometry": {
                "type": "Point",
                "coordinates": [
                    -70.59376182300412,
                    -33.44640990906889
                ]
            }
        },
        {
            "type": "Feature",
            "properties": {
                "identifier": "m8t6hwlzxxap3b",
                "name": "Baño",
                "information": "",
                "categories": [
                    "bath"
                ],
                "campus": "OR",
                "faculties": "",
                "floors": [
                    -1
                ],
                "needApproval": true
            },
            "geometry": {
                "type": "Point",
                "coordinates": [
                    -70.59380761258232,
                    -33.44646992526883
                ]
            }
        },
        {
            "type": "Feature",
            "properties": {
                "identifier": "m8t6hbz1y4mvkl",
                "name": "Salón Multiuso",
                "information": "",
                "categories": [
                    "auditorium"
                ],
                "campus": "OR",
                "faculties": "",
                "floors": [
                    -1
                ],
                "needApproval": true
            },
            "geometry": {
                "type": "Point",
                "coordinates": [
                    -70.5936297302673,
                    -33.44663981405564
                ]
            }
        },
        {
            "type": "Feature",
            "properties": {
                "identifier": "m8t6fwcpg8qdkt",
                "name": "Teatro",
                "information": "",
                "categories": [
                    "auditorium"
                ],
                "campus": "OR",
                "faculties": "",
                "floors": [
                    -1
                ],
                "needApproval": true
            },
            "geometry": {
                "type": "Point",
                "coordinates": [
                    -70.5936633905187,
                    -33.446612012507636
                ]
            }
        },
        {
            "type": "Feature",
            "properties": {
                "identifier": "m8t6esp4pi0loc",
                "name": "Castaño",
                "information": "",
                "categories": [
                    "food_lunch"
                ],
                "campus": "OR",
                "faculties": "",
                "floors": [
                    1
                ],
                "needApproval": true
            },
            "geometry": {
                "type": "Point",
                "coordinates": [
                    -70.59377466438089,
                    -33.446592941606376
                ]
            }
        },
        {
            "type": "Feature",
            "properties": {
                "identifier": "m8t6ercvjqhnqk",
                "name": "Castaño",
                "information": "",
                "categories": [
                    "food_lunch"
                ],
                "campus": "OR",
                "faculties": "",
                "floors": [
                    1
                ],
                "needApproval": true
            },
            "geometry": {
                "type": "Point",
                "coordinates": [
                    -70.59377466438089,
                    -33.446592941606376
                ]
            }
        },
        {
            "type": "Feature",
            "properties": {
                "identifier": "m8t6dn9etutve4",
                "name": "Librería UC",
                "information": "",
                "categories": [
                    "shop"
                ],
                "campus": "OR",
                "faculties": "",
                "floors": [
                    1
                ],
                "needApproval": true
            },
            "geometry": {
                "type": "Point",
                "coordinates": [
                    -70.5938526433071,
                    -33.446447328589926
                ]
            }
        },
        {
            "type": "Feature",
            "properties": {
                "identifier": "m8t6b8nomiba3q",
                "name": "Casa del coro",
                "information": "",
                "categories": [
                    "other"
                ],
                "campus": "OR",
                "faculties": "",
                "floors": [
                    1
                ],
                "needApproval": true
            },
            "geometry": {
                "type": "Point",
                "coordinates": [
                    -70.59416320198417,
                    -33.44684624060388
                ]
            }
        },
        {
            "type": "Feature",
            "properties": {
                "identifier": "m8qm6hw5gb4hys",
                "name": "CAI",
                "information": "",
                "categories": [
                    "other"
                ],
                "campus": "SJ",
                "faculties": "",
                "floors": [
                    1
                ],
                "needApproval": true
            },
            "geometry": {
                "type": "Point",
                "coordinates": [
                    -70.61327872937629,
                    -33.49990057479303
                ]
            }
        },
        {
            "type": "Feature",
            "properties": {
                "identifier": "m8hwvs9z7x10a8",
                "name": "Agua",
                "information": "Hay agua fria y caliente!",
                "categories": [
                    "water"
                ],
                "campus": "SJ",
                "faculties": "",
                "floors": [
                    1
                ],
                "needApproval": true
            },
            "geometry": {
                "type": "Point",
                "coordinates": [
                    -70.60963001716996,
                    -33.49971641958577
                ]
            }
        }
    ]
}